aidf_verbose_logs/__init__.py
aidf_verbose_logs/logger.py
aidf_verbose_logs-0.1.6.dist-info/METADATA
aidf_verbose_logs-0.1.6.dist-info/WHEEL
aidf_verbose_logs-0.1.6.dist-info/top_level.txt
aidf_verbose_logs-0.1.6.dist-info/RECORD
