Metadata-Version: 2.4
Name: aidf-verbose-logs
Version: 0.1.6
Summary: Verbose logger for AIDF
Author-email: Kaustubh Paturi <plutofeb115@gmail.com>
License: MIT
Project-URL: Homepage, https://github.com/paturikaustubh/aidf-verbose-logs
Project-URL: Bug Tracker, https://github.com/paturikaustubh/aidf-verbose-logs/issues
Classifier: Programming Language :: Python :: 3
Classifier: License :: OSI Approved :: MIT License
Classifier: Operating System :: OS Independent
Requires-Python: >=3.7
Requires-Dist: psycopg2>=2.9.10
